spark_dummy_tools/__init__.py
spark_dummy_tools/functions/__init__.py
spark_dummy_tools/functions/generator.py
spark_dummy_tools-0.8.3.dist-info/LICENSE
spark_dummy_tools-0.8.3.dist-info/METADATA
spark_dummy_tools-0.8.3.dist-info/WHEEL
spark_dummy_tools-0.8.3.dist-info/top_level.txt
spark_dummy_tools-0.8.3.dist-info/RECORD
